{
  "formatVersion": 1,
  "database": {
    "version": 10,
    "identityHash": "4bf7e0183c283a308d2161bde0651b13",
    "entities": [
      {
        "tableName": "habits",
        "createSql": "CREATE TABLE IF NOT EXISTS `${TABLE_NAME}` (`id` INTEGER PRIMARY KEY AUTOINCREMENT NOT NULL, `title` TEXT NOT NULL, `description` TEXT NOT NULL, `color` TEXT NOT NULL, `icon` TEXT NOT NULL, `targetDays` INTEGER NOT NULL, `isActive` INTEGER NOT NULL, `scheduledTime` TEXT NOT NULL, `createdAt` INTEGER NOT NULL)",
        "fields": [
          {
            "fieldPath": "id",
            "columnName": "id",
            "affinity": "INTEGER",
            "notNull": true
          },
          {
            "fieldPath": "title",
            "columnName": "title",
            "affinity": "TEXT",
            "notNull": true
          },
          {
            "fieldPath": "description",
            "columnName": "description",
            "affinity": "TEXT",
            "notNull": true
          },
          {
            "fieldPath": "color",
            "columnName": "color",
            "affinity": "TEXT",
            "notNull": true
          },
          {
            "fieldPath": "icon",
            "columnName": "icon",
            "affinity": "TEXT",
            "notNull": true
          },
          {
            "fieldPath": "targetDays",
            "columnName": "targetDays",
            "affinity": "INTEGER",
            "notNull": true
          },
          {
            "fieldPath": "isActive",
            "columnName": "isActive",
            "affinity": "INTEGER",
            "notNull": true
          },
          {
            "fieldPath": "scheduledTime",
            "columnName": "scheduledTime",
            "affinity": "TEXT",
            "notNull": true
          },
          {
            "fieldPath": "createdAt",
            "columnName": "createdAt",
            "affinity": "INTEGER",
            "notNull": true
          }
        ],
        "primaryKey": {
          "autoGenerate": true,
          "columnNames": [
            "id"
          ]
        },
        "indices": [],
        "foreignKeys": []
      },
      {
        "tableName": "habit_completions",
        "createSql": "CREATE TABLE IF NOT EXISTS `${TABLE_NAME}` (`id` INTEGER PRIMARY KEY AUTOINCREMENT NOT NULL, `habitId` INTEGER NOT NULL, `date` TEXT NOT NULL, `completedAt` INTEGER NOT NULL)",
        "fields": [
          {
            "fieldPath": "id",
            "columnName": "id",
            "affinity": "INTEGER",
            "notNull": true
          },
          {
            "fieldPath": "habitId",
            "columnName": "habitId",
            "affinity": "INTEGER",
            "notNull": true
          },
          {
            "fieldPath": "date",
            "columnName": "date",
            "affinity": "TEXT",
            "notNull": true
          },
          {
            "fieldPath": "completedAt",
            "columnName": "completedAt",
            "affinity": "INTEGER",
            "notNull": true
          }
        ],
        "primaryKey": {
          "autoGenerate": true,
          "columnNames": [
            "id"
          ]
        },
        "indices": [],
        "foreignKeys": []
      },
      {
        "tableName": "notifications",
        "createSql": "CREATE TABLE IF NOT EXISTS `${TABLE_NAME}` (`id` INTEGER PRIMARY KEY AUTOINCREMENT NOT NULL, `title` TEXT NOT NULL, `message` TEXT NOT NULL, `type` TEXT NOT NULL, `habitId` INTEGER, `habitTitle` TEXT, `createdAt` TEXT NOT NULL, `isRead` INTEGER NOT NULL)",
        "fields": [
          {
            "fieldPath": "id",
            "columnName": "id",
            "affinity": "INTEGER",
            "notNull": true
          },
          {
            "fieldPath": "title",
            "columnName": "title",
            "affinity": "TEXT",
            "notNull": true
          },
          {
            "fieldPath": "message",
            "columnName": "message",
            "affinity": "TEXT",
            "notNull": true
          },
          {
            "fieldPath": "type",
            "columnName": "type",
            "affinity": "TEXT",
            "notNull": true
          },
          {
            "fieldPath": "habitId",
            "columnName": "habitId",
            "affinity": "INTEGER",
            "notNull": false
          },
          {
            "fieldPath": "habitTitle",
            "columnName": "habitTitle",
            "affinity": "TEXT",
            "notNull": false
          },
          {
            "fieldPath": "createdAt",
            "columnName": "createdAt",
            "affinity": "TEXT",
            "notNull": true
          },
          {
            "fieldPath": "isRead",
            "columnName": "isRead",
            "affinity": "INTEGER",
            "notNull": true
          }
        ],
        "primaryKey": {
          "autoGenerate": true,
          "columnNames": [
            "id"
          ]
        },
        "indices": [],
        "foreignKeys": []
      },
      {
        "tableName": "user_profile",
        "createSql": "CREATE TABLE IF NOT EXISTS `${TABLE_NAME}` (`id` INTEGER NOT NULL, `name` TEXT NOT NULL, `createdAt` INTEGER NOT NULL, PRIMARY KEY(`id`))",
        "fields": [
          {
            "fieldPath": "id",
            "columnName": "id",
            "affinity": "INTEGER",
            "notNull": true
          },
          {
            "fieldPath": "name",
            "columnName": "name",
            "affinity": "TEXT",
            "notNull": true
          },
          {
            "fieldPath": "createdAt",
            "columnName": "createdAt",
            "affinity": "INTEGER",
            "notNull": true
          }
        ],
        "primaryKey": {
          "autoGenerate": false,
          "columnNames": [
            "id"
          ]
        },
        "indices": [],
        "foreignKeys": []
      }
    ],
    "views": [],
    "setupQueries": [
      "CREATE TABLE IF NOT EXISTS room_master_table (id INTEGER PRIMARY KEY,identity_hash TEXT)",
      "INSERT OR REPLACE INTO room_master_table (id,identity_hash) VALUES(42, '4bf7e0183c283a308d2161bde0651b13')"
    ]
  }
}